src/top.sv
`timescale 1ns/100ps

module top #(
) (
    input  logic       CLOCK_50,
    input  logic [9:0] SW,
    input  logic       audio_in_available,
    input  logic       audio_out_allowed, 
    output logic       read_audio_in,   
    output logic       write_audio_out, 

    input  logic signed [31:0] audio_in_L,
    input  logic signed [31:0] audio_in_R,
    output logic signed [31:0] audio_out_L,
    output logic signed [31:0] audio_out_R
);

logic signed [31:0] l_processed, r_processed;

assign read_audio_in = audio_in_available && audio_out_allowed;
assign write_audio_out = audio_in_available && audio_out_allowed;

always_ff @(posedge CLOCK_50) begin
    if (read_audio_in) begin
        // Get audio input
        l_processed = audio_in_L;
        r_processed = audio_in_R;

        // Apply effects based on switches
        if (SW[0]) begin
            l_processed = 0;
            r_processed = 0;
        end

        // Output processed audio channels
        audio_out_L <= l_processed;
        audio_out_R <= r_processed;
    end
end



endmodule

test/tb.sv
`timescale 1ns/100ps

module tb;

    // --- Signal Declarations ---
    logic CLOCK_50;
    logic [9:0] SW;
    logic audio_in_available;
    logic audio_out_allowed;
    logic signed [31:0] audio_in_L, audio_in_R;
    logic read_audio_in, write_audio_out;
    logic signed [31:0] audio_out_L, audio_out_R;

    // --- UUT Instantiation ---
    top uut (
        .CLOCK_50(CLOCK_50),
        .SW(SW),
        .audio_in_available(audio_in_available),
        .audio_out_allowed(audio_out_allowed),
        .read_audio_in(read_audio_in),
        .write_audio_out(write_audio_out),
        .audio_in_L(audio_in_L),
        .audio_in_R(audio_in_R),
        .audio_out_L(audio_out_L),
        .audio_out_R(audio_out_R)
    );

    // --- Clock Generation ---
    initial begin
        CLOCK_50 = 0;
        forever #10 CLOCK_50 = ~CLOCK_50;
    end

    // --- MAIN TEST SEQUENCE ---
    initial begin
        $dumpfile("sim_out/wave.vcd");
        $dumpvars(0, tb);

        // 1. Initialize
        SW = 0;
        audio_in_available = 0;
        audio_out_allowed = 0;
        audio_in_L = 0;
        audio_in_R = 0;
        #100;

        $display("--- Simulation Start ---");

        // ============================================================
        // TEST 1: Passthrough
        // ============================================================
        $display("\nTest 1: Normal Passthrough");
        
        // Setup
        audio_in_L = 32'd1000;
        audio_in_R = -32'd1000;

        // Handshake
        @(posedge CLOCK_50);
        audio_in_available = 1;
        audio_out_allowed = 1;

        // Wait for Logic to respond
        wait(read_audio_in == 1);
        @(posedge CLOCK_50); // Latch Data

        // Verify
        if (audio_out_L == 1000 && audio_out_R == -1000) 
            $display("  -> PASS");
        else 
            $display("  -> FAIL: Got %d / %d", audio_out_L, audio_out_R);

        // Reset
        audio_in_available = 0;
        audio_out_allowed = 0;
        #50;

        // ============================================================
        // TEST 2: Mute
        // ============================================================
        $display("\nTest 2: Mute Function");

        // Setup
        SW[0] = 1; 
        audio_in_L = 32'd5000;
        audio_in_R = 32'd5000;

        // Handshake
        @(posedge CLOCK_50);
        audio_in_available = 1;
        audio_out_allowed = 1;

        // Wait
        wait(read_audio_in == 1);
        @(posedge CLOCK_50);

        // Verify
        if (audio_out_L == 0)
            $display("  -> PASS");
        else
            $display("  -> FAIL: Got %d", audio_out_L);

        // Reset
        SW[0] = 0; // Turn mute off for next test
        audio_in_available = 0;
        audio_out_allowed = 0;
        #50;

        // ============================================================
        // TEST 3: Pipeline Timing Check (The "Trap")
        // ============================================================
        $display("\nTest 3: Checking for Sequential Timing Accuracy");
        
        // Setup distinctive data
        audio_in_L = 32'hDEADBEEF;
        audio_in_R = 32'hDEADBEEF;

        // Handshake
        @(posedge CLOCK_50);
        audio_in_available = 1;
        audio_out_allowed = 1;

        // Wait for the WRITE signal
        wait(write_audio_out == 1);
        
        // Sample at the exact moment WRITE goes high
        // If your logic is sequential, data should be ready NOW.
        @(posedge CLOCK_50); 

        // Verify
        if (audio_out_L === 32'hDEADBEEF) begin
            $display("  -> PASS: Data valid exactly when Write asserted.");
        end else begin
            $display("  -> FAIL: Timing Mismatch!");
            $display("     Expected: DEADBEEF");
            $display("     Got:      %h", audio_out_L);
        end

        $display("\n--- Simulation End ---");
        $finish;
    end

endmodule

.github/outputs/wave.vcd
$version Generated by VerilatedVcd $end
$timescale 100ps $end
 $scope module TOP $end
  $scope module tb $end
   $var wire 1 . CLOCK_50 $end
   $var wire 10 # SW [9:0] $end
   $var wire 1 $ audio_in_available $end
   $var wire 1 % audio_out_allowed $end
   $var wire 32 & audio_in_L [31:0] $end
   $var wire 32 ' audio_in_R [31:0] $end
   $var wire 1 ( read_audio_in $end
   $var wire 1 ) write_audio_out $end
   $var wire 32 * audio_out_L [31:0] $end
   $var wire 32 + audio_out_R [31:0] $end
   $scope module uut $end
    $var wire 1 . CLOCK_50 $end
    $var wire 10 # SW [9:0] $end
    $var wire 1 $ audio_in_available $end
    $var wire 1 % audio_out_allowed $end
    $var wire 1 ( read_audio_in $end
    $var wire 1 ) write_audio_out $end
    $var wire 32 & audio_in_L [31:0] $end
    $var wire 32 ' audio_in_R [31:0] $end
    $var wire 32 * audio_out_L [31:0] $end
    $var wire 32 + audio_out_R [31:0] $end
    $var wire 32 , l_processed [31:0] $end
    $var wire 32 - r_processed [31:0] $end
   $upscope $end
  $upscope $end
 $upscope $end
$enddefinitions $end


#0
b0000000000 #
0$
0%
b00000000000000000000000000000000 &
b00000000000000000000000000000000 '
0(
0)
b00000000000000000000000000000000 *
b00000000000000000000000000000000 +
b00000000000000000000000000000000 ,
b00000000000000000000000000000000 -
0.
#100
1.
#200
0.
#300
1.
#400
0.
#500
1.
#600
0.
#700
1.
#800
0.
#900
1.
#1000
b00000000000000000000001111101000 &
b11111111111111111111110000011000 '
0.
#1100
1$
1%
1(
1)
b00000000000000000000001111101000 *
b11111111111111111111110000011000 +
b00000000000000000000001111101000 ,
b11111111111111111111110000011000 -
1.
#1200
0.
#1300
0$
0%
0(
0)
1.
#1400
0.
#1500
1.
#1600
0.
#1700
1.
#1800
b0000000001 #
b00000000000000000001001110001000 &
b00000000000000000001001110001000 '
0.
#1900
1$
1%
1(
1)
b00000000000000000000000000000000 *
b00000000000000000000000000000000 +
b00000000000000000000000000000000 ,
b00000000000000000000000000000000 -
1.
#2000
0.
#2100
b0000000000 #
0$
0%
0(
0)
1.
#2200
0.
#2300
1.
#2400
0.
#2500
1.
#2600
b11011110101011011011111011101111 &
b11011110101011011011111011101111 '
0.
#2700
1$
1%
1(
1)
b11011110101011011011111011101111 *
b11011110101011011011111011101111 +
b11011110101011011011111011101111 ,
b11011110101011011011111011101111 -
1.
