src/top.sv
`timescale 1ns/100ps

module top #(
) (
    input  logic       CLOCK_50,
    input  logic [9:0] SW,
    input  logic       audio_in_available,
    input  logic       audio_out_allowed, 
    output logic       read_audio_in,   
    output logic       write_audio_out, 

    input  logic signed [31:0] audio_in_L,
    input  logic signed [31:0] audio_in_R,
    output logic signed [31:0] audio_out_L,
    output logic signed [31:0] audio_out_R
);

logic signed [31:0] l_processed, r_processed;

assign read_audio_in = audio_in_available && audio_out_allowed;
assign write_audio_out = audio_in_available && audio_out_allowed;

always_ff @(posedge CLOCK_50) begin
    if (read_audio_in) begin
        // Get audio input
        l_processed = audio_in_L;
        r_processed = audio_in_R;

        // Apply effects based on switches
        if (SW[0]) begin
            l_processed = 0;
            r_processed = 0;
        end

        // Output processed audio channels
        audio_out_L <= l_processed;
        audio_out_R <= r_processed;
    end
end



endmodule

test/tb.sv
`timescale 1ns/100ps

module tb;

    // --- Signal Declarations ---
    logic CLOCK_50;
    logic [9:0] SW;
    logic audio_in_available;
    logic audio_out_allowed;
    logic signed [31:0] audio_in_L, audio_in_R;
    logic read_audio_in, write_audio_out;
    logic signed [31:0] audio_out_L, audio_out_R;

    // Test tracking
    integer test_count = 0;
    integer pass_count = 0;
    integer fail_count = 0;
    
    // Helper variables
    logic signed [31:0] prev_out_L, prev_out_R;

    // --- UUT Instantiation ---
    top uut (
        .CLOCK_50(CLOCK_50),
        .SW(SW),
        .audio_in_available(audio_in_available),
        .audio_out_allowed(audio_out_allowed),
        .read_audio_in(read_audio_in),
        .write_audio_out(write_audio_out),
        .audio_in_L(audio_in_L),
        .audio_in_R(audio_in_R),
        .audio_out_L(audio_out_L),
        .audio_out_R(audio_out_R)
    );

    // --- Clock Generation ---
    initial begin
        CLOCK_50 = 0;
        forever #10 CLOCK_50 = ~CLOCK_50;
    end

    // --- Helper Task for Checking Results ---
    task check_audio_output(
        input signed [31:0] expected_L,
        input signed [31:0] expected_R,
        input string test_name
    );
        test_count = test_count + 1;
        if (audio_out_L === expected_L && audio_out_R === expected_R) begin
            $display("  -> PASS: %s", test_name);
            $display("LOG: %0t : INFO : tb : uut.audio_out_L : expected_value: %0d actual_value: %0d", $time, expected_L, audio_out_L);
            $display("LOG: %0t : INFO : tb : uut.audio_out_R : expected_value: %0d actual_value: %0d", $time, expected_R, audio_out_R);
            pass_count = pass_count + 1;
        end else begin
            $display("  -> FAIL: %s", test_name);
            $display("LOG: %0t : ERROR : tb : uut.audio_out_L : expected_value: %0d actual_value: %0d", $time, expected_L, audio_out_L);
            $display("LOG: %0t : ERROR : tb : uut.audio_out_R : expected_value: %0d actual_value: %0d", $time, expected_R, audio_out_R);
            fail_count = fail_count + 1;
        end
    endtask

    // --- MAIN TEST SEQUENCE ---
    initial begin
        $dumpfile("sim_out/wave.vcd");
        $dumpvars(0, tb);
        $display("TEST START");

        // Initialize
        SW = 0;
        audio_in_available = 0;
        audio_out_allowed = 0;
        audio_in_L = 0;
        audio_in_R = 0;
        #100;

        $display("\n=== Audio Processing Module Test Suite ===\n");

        // ============================================================
        // TEST 1: Normal Passthrough
        // ============================================================
        $display("\nTest 1: Normal Passthrough");
        
        audio_in_L = 32'd1000;
        audio_in_R = -32'd1000;

        @(posedge CLOCK_50);
        audio_in_available = 1;
        audio_out_allowed = 1;

        wait(read_audio_in == 1);
        @(posedge CLOCK_50);

        check_audio_output(32'd1000, -32'd1000, "Basic passthrough");

        audio_in_available = 0;
        audio_out_allowed = 0;
        #50;

        // ============================================================
        // TEST 2: Mute Function
        // ============================================================
        $display("\nTest 2: Mute Function");

        SW[0] = 1; 
        audio_in_L = 32'd5000;
        audio_in_R = 32'd5000;

        @(posedge CLOCK_50);
        audio_in_available = 1;
        audio_out_allowed = 1;

        wait(read_audio_in == 1);
        @(posedge CLOCK_50);

        check_audio_output(32'd0, 32'd0, "Mute both channels");

        SW[0] = 0;
        audio_in_available = 0;
        audio_out_allowed = 0;
        #50;

        // ============================================================
        // TEST 3: Pipeline Timing Check
        // ============================================================
        $display("\nTest 3: Sequential Timing Accuracy");
        
        audio_in_L = 32'hDEADBEEF;
        audio_in_R = 32'hDEADBEEF;

        @(posedge CLOCK_50);
        audio_in_available = 1;
        audio_out_allowed = 1;

        wait(write_audio_out == 1);
        @(posedge CLOCK_50);

        check_audio_output(32'hDEADBEEF, 32'hDEADBEEF, "Timing check");

        audio_in_available = 0;
        audio_out_allowed = 0;
        #50;

        // ============================================================
        // TEST 4: Maximum Positive Values
        // ============================================================
        $display("\nTest 4: Maximum Positive Values");
        
        audio_in_L = 32'h7FFFFFFF;  // Max positive signed 32-bit
        audio_in_R = 32'h7FFFFFFF;

        @(posedge CLOCK_50);
        audio_in_available = 1;
        audio_out_allowed = 1;

        wait(read_audio_in == 1);
        @(posedge CLOCK_50);

        check_audio_output(32'h7FFFFFFF, 32'h7FFFFFFF, "Max positive values");

        audio_in_available = 0;
        audio_out_allowed = 0;
        #50;

        // ============================================================
        // TEST 5: Maximum Negative Values
        // ============================================================
        $display("\nTest 5: Maximum Negative Values");
        
        audio_in_L = 32'h80000000;  // Max negative signed 32-bit
        audio_in_R = 32'h80000000;

        @(posedge CLOCK_50);
        audio_in_available = 1;
        audio_out_allowed = 1;

        wait(read_audio_in == 1);
        @(posedge CLOCK_50);

        check_audio_output(32'h80000000, 32'h80000000, "Max negative values");

        audio_in_available = 0;
        audio_out_allowed = 0;
        #50;

        // ============================================================
        // TEST 6: Mute with Maximum Values
        // ============================================================
        $display("\nTest 6: Mute with Maximum Values");
        
        SW[0] = 1;
        audio_in_L = 32'h7FFFFFFF;
        audio_in_R = 32'h80000000;

        @(posedge CLOCK_50);
        audio_in_available = 1;
        audio_out_allowed = 1;

        wait(read_audio_in == 1);
        @(posedge CLOCK_50);

        check_audio_output(32'd0, 32'd0, "Mute overrides max values");

        SW[0] = 0;
        audio_in_available = 0;
        audio_out_allowed = 0;
        #50;

        // ============================================================
        // TEST 7: Only audio_in_available High
        // ============================================================
        $display("\nTest 7: Incomplete Handshake - Only audio_in_available");
        
        audio_in_L = 32'd12345;
        audio_in_R = 32'd67890;
        
        prev_out_L = audio_out_L;
        prev_out_R = audio_out_R;

        @(posedge CLOCK_50);
        audio_in_available = 1;
        audio_out_allowed = 0;  // Not allowed

        @(posedge CLOCK_50);
        @(posedge CLOCK_50);

        test_count = test_count + 1;
        if (read_audio_in === 0 && write_audio_out === 0) begin
            $display("  -> PASS: Handshake signals remain low");
            $display("LOG: %0t : INFO : tb : uut.read_audio_in : expected_value: 0 actual_value: %0d", $time, read_audio_in);
            pass_count = pass_count + 1;
        end else begin
            $display("  -> FAIL: Handshake should not activate");
            $display("LOG: %0t : ERROR : tb : uut.read_audio_in : expected_value: 0 actual_value: %0d", $time, read_audio_in);
            fail_count = fail_count + 1;
        end

        audio_in_available = 0;
        #50;

        // ============================================================
        // TEST 8: Only audio_out_allowed High
        // ============================================================
        $display("\nTest 8: Incomplete Handshake - Only audio_out_allowed");
        
        audio_in_L = 32'd99999;
        audio_in_R = 32'd88888;

        @(posedge CLOCK_50);
        audio_in_available = 0;  // Not available
        audio_out_allowed = 1;

        @(posedge CLOCK_50);
        @(posedge CLOCK_50);

        test_count = test_count + 1;
        if (read_audio_in === 0 && write_audio_out === 0) begin
            $display("  -> PASS: Handshake signals remain low");
            $display("LOG: %0t : INFO : tb : uut.write_audio_out : expected_value: 0 actual_value: %0d", $time, write_audio_out);
            pass_count = pass_count + 1;
        end else begin
            $display("  -> FAIL: Handshake should not activate");
            $display("LOG: %0t : ERROR : tb : uut.write_audio_out : expected_value: 0 actual_value: %0d", $time, write_audio_out);
            fail_count = fail_count + 1;
        end

        audio_out_allowed = 0;
        #50;

        // ============================================================
        // TEST 9: Sequential Audio Samples
        // ============================================================
        $display("\nTest 9: Sequential Audio Samples");
        
        // Sample 1
        audio_in_L = 32'd100;
        audio_in_R = 32'd200;
        @(posedge CLOCK_50);
        audio_in_available = 1;
        audio_out_allowed = 1;
        wait(read_audio_in == 1);
        @(posedge CLOCK_50);
        check_audio_output(32'd100, 32'd200, "Sequential sample 1");
        
        // Sample 2 - immediately following
        audio_in_L = 32'd300;
        audio_in_R = 32'd400;
        @(posedge CLOCK_50);
        check_audio_output(32'd300, 32'd400, "Sequential sample 2");
        
        // Sample 3
        audio_in_L = -32'd500;
        audio_in_R = -32'd600;
        @(posedge CLOCK_50);
        check_audio_output(-32'd500, -32'd600, "Sequential sample 3");

        audio_in_available = 0;
        audio_out_allowed = 0;
        #50;

        // ============================================================
        // TEST 10: Unused Switches Don't Interfere
        // ============================================================
        $display("\nTest 10: Unused Switches Verification");
        
        SW = 10'b1111111110;  // All switches except SW[0]
        audio_in_L = 32'd7777;
        audio_in_R = 32'd8888;

        @(posedge CLOCK_50);
        audio_in_available = 1;
        audio_out_allowed = 1;

        wait(read_audio_in == 1);
        @(posedge CLOCK_50);

        check_audio_output(32'd7777, 32'd8888, "Unused switches don't affect passthrough");

        SW = 0;
        audio_in_available = 0;
        audio_out_allowed = 0;
        #50;

        // ============================================================
        // TEST 11: Asymmetric Channel Values
        // ============================================================
        $display("\nTest 11: Asymmetric Channel Values");
        
        audio_in_L = 32'h7FFFFFFF;
        audio_in_R = 32'h80000000;

        @(posedge CLOCK_50);
        audio_in_available = 1;
        audio_out_allowed = 1;

        wait(read_audio_in == 1);
        @(posedge CLOCK_50);

        check_audio_output(32'h7FFFFFFF, 32'h80000000, "Max positive L, max negative R");

        audio_in_available = 0;
        audio_out_allowed = 0;
        #50;

        // ============================================================
        // TEST 12: Zero Audio Values
        // ============================================================
        $display("\nTest 12: Zero Audio Values");
        
        audio_in_L = 32'd0;
        audio_in_R = 32'd0;

        @(posedge CLOCK_50);
        audio_in_available = 1;
        audio_out_allowed = 1;

        wait(read_audio_in == 1);
        @(posedge CLOCK_50);

        check_audio_output(32'd0, 32'd0, "Zero values passthrough");

        audio_in_available = 0;
        audio_out_allowed = 0;
        #50;

        // ============================================================
        // TEST 13: Rapid Enable/Disable
        // ============================================================
        $display("\nTest 13: Rapid Handshake Toggling");
        
        audio_in_L = 32'd4444;
        audio_in_R = 32'd5555;

        // Quick enable
        @(posedge CLOCK_50);
        audio_in_available = 1;
        audio_out_allowed = 1;
        
        // One cycle only
        @(posedge CLOCK_50);
        audio_in_available = 0;
        audio_out_allowed = 0;
        
        @(posedge CLOCK_50);
        
        test_count = test_count + 1;
        if (read_audio_in === 0 && write_audio_out === 0) begin
            $display("  -> PASS: Signals deasserted after handshake removed");
            $display("LOG: %0t : INFO : tb : uut.read_audio_in : expected_value: 0 actual_value: %0d", $time, read_audio_in);
            pass_count = pass_count + 1;
        end else begin
            $display("  -> FAIL: Signals should follow handshake");
            $display("LOG: %0t : ERROR : tb : uut.read_audio_in : expected_value: 0 actual_value: %0d", $time, read_audio_in);
            fail_count = fail_count + 1;
        end
        
        #50;

        // ============================================================
        // TEST 14: Mute Toggle During Operation
        // ============================================================
        $display("\nTest 14: Mute Toggle During Operation");
        
        // Start with audio
        SW[0] = 0;
        audio_in_L = 32'd2000;
        audio_in_R = 32'd3000;

        @(posedge CLOCK_50);
        audio_in_available = 1;
        audio_out_allowed = 1;
        wait(read_audio_in == 1);
        @(posedge CLOCK_50);
        check_audio_output(32'd2000, 32'd3000, "Before mute toggle");

        // Toggle mute on
        SW[0] = 1;
        audio_in_L = 32'd2000;
        audio_in_R = 32'd3000;
        @(posedge CLOCK_50);
        check_audio_output(32'd0, 32'd0, "After mute enabled");

        // Toggle mute off
        SW[0] = 0;
        audio_in_L = 32'd2000;
        audio_in_R = 32'd3000;
        @(posedge CLOCK_50);
        check_audio_output(32'd2000, 32'd3000, "After mute disabled");

        audio_in_available = 0;
        audio_out_allowed = 0;
        SW[0] = 0;
        #50;

        // ============================================================
        // Test Summary
        // ============================================================
        $display("\n=== Test Summary ===");
        $display("Total Tests: %0d", test_count);
        $display("Passed:      %0d", pass_count);
        $display("Failed:      %0d", fail_count);
        
        if (fail_count == 0) begin
            $display("\nTEST PASSED");
        end else begin
            $display("\nTEST FAILED");
        end

        $finish;
    end

endmodule

.github/outputs/wave.vcd
$version Generated by VerilatedVcd $end
$timescale 100ps $end
 $scope module TOP $end
  $scope module tb $end
   $var wire 1 3 CLOCK_50 $end
   $var wire 10 # SW [9:0] $end
   $var wire 1 $ audio_in_available $end
   $var wire 1 % audio_out_allowed $end
   $var wire 32 & audio_in_L [31:0] $end
   $var wire 32 ' audio_in_R [31:0] $end
   $var wire 1 - read_audio_in $end
   $var wire 1 . write_audio_out $end
   $var wire 32 / audio_out_L [31:0] $end
   $var wire 32 0 audio_out_R [31:0] $end
   $var wire 32 ( test_count [31:0] $end
   $var wire 32 ) pass_count [31:0] $end
   $var wire 32 * fail_count [31:0] $end
   $var wire 32 + prev_out_L [31:0] $end
   $var wire 32 , prev_out_R [31:0] $end
   $scope module uut $end
    $var wire 1 3 CLOCK_50 $end
    $var wire 10 # SW [9:0] $end
    $var wire 1 $ audio_in_available $end
    $var wire 1 % audio_out_allowed $end
    $var wire 1 - read_audio_in $end
    $var wire 1 . write_audio_out $end
    $var wire 32 & audio_in_L [31:0] $end
    $var wire 32 ' audio_in_R [31:0] $end
    $var wire 32 / audio_out_L [31:0] $end
    $var wire 32 0 audio_out_R [31:0] $end
    $var wire 32 1 l_processed [31:0] $end
    $var wire 32 2 r_processed [31:0] $end
   $upscope $end
  $upscope $end
 $upscope $end
$enddefinitions $end


#0
b0000000000 #
0$
0%
b00000000000000000000000000000000 &
b00000000000000000000000000000000 '
b00000000000000000000000000000000 (
b00000000000000000000000000000000 )
b00000000000000000000000000000000 *
b00000000000000000000000000000000 +
b00000000000000000000000000000000 ,
0-
0.
b00000000000000000000000000000000 /
b00000000000000000000000000000000 0
b00000000000000000000000000000000 1
b00000000000000000000000000000000 2
03
#100
13
#200
03
#300
13
#400
03
#500
13
#600
03
#700
13
#800
03
#900
13
#1000
b00000000000000000000001111101000 &
b11111111111111111111110000011000 '
03
#1100
1$
1%
1-
1.
b00000000000000000000001111101000 /
b11111111111111111111110000011000 0
b00000000000000000000001111101000 1
b11111111111111111111110000011000 2
13
#1200
03
#1300
0$
0%
b00000000000000000000000000000001 (
b00000000000000000000000000000001 )
0-
0.
13
#1400
03
#1500
13
#1600
03
#1700
13
#1800
b0000000001 #
b00000000000000000001001110001000 &
b00000000000000000001001110001000 '
03
#1900
1$
1%
1-
1.
b00000000000000000000000000000000 /
b00000000000000000000000000000000 0
b00000000000000000000000000000000 1
b00000000000000000000000000000000 2
13
#2000
03
#2100
b0000000000 #
0$
0%
b00000000000000000000000000000010 (
b00000000000000000000000000000010 )
0-
0.
13
#2200
03
#2300
13
#2400
03
#2500
13
#2600
b11011110101011011011111011101111 &
b11011110101011011011111011101111 '
03
#2700
1$
1%
1-
1.
b11011110101011011011111011101111 /
b11011110101011011011111011101111 0
b11011110101011011011111011101111 1
b11011110101011011011111011101111 2
13
#2800
03
#2900
0$
0%
b00000000000000000000000000000011 (
b00000000000000000000000000000011 )
0-
0.
13
#3000
03
#3100
13
#3200
03
#3300
13
#3400
b01111111111111111111111111111111 &
b01111111111111111111111111111111 '
03
#3500
1$
1%
1-
1.
b01111111111111111111111111111111 /
b01111111111111111111111111111111 0
b01111111111111111111111111111111 1
b01111111111111111111111111111111 2
13
#3600
03
#3700
0$
0%
b00000000000000000000000000000100 (
b00000000000000000000000000000100 )
0-
0.
13
#3800
03
#3900
13
#4000
03
#4100
13
#4200
b10000000000000000000000000000000 &
b10000000000000000000000000000000 '
03
#4300
1$
1%
1-
1.
b10000000000000000000000000000000 /
b10000000000000000000000000000000 0
b10000000000000000000000000000000 1
b10000000000000000000000000000000 2
13
#4400
03
#4500
0$
0%
b00000000000000000000000000000101 (
b00000000000000000000000000000101 )
0-
0.
13
#4600
03
#4700
13
#4800
03
#4900
13
#5000
b0000000001 #
b01111111111111111111111111111111 &
03
#5100
1$
1%
1-
1.
b00000000000000000000000000000000 /
b00000000000000000000000000000000 0
b00000000000000000000000000000000 1
b00000000000000000000000000000000 2
13
#5200
03
#5300
b0000000000 #
0$
0%
b00000000000000000000000000000110 (
b00000000000000000000000000000110 )
0-
0.
13
#5400
03
#5500
13
#5600
03
#5700
13
#5800
b00000000000000000011000000111001 &
b00000000000000010000100100110010 '
03
#5900
1$
13
#6000
03
#6100
13
#6200
03
#6300
0$
b00000000000000000000000000000111 (
b00000000000000000000000000000111 )
13
#6400
03
#6500
13
#6600
03
#6700
13
#6800
b00000000000000011000011010011111 &
b00000000000000010101101100111000 '
03
#6900
1%
13
#7000
03
#7100
13
#7200
03
#7300
0%
b00000000000000000000000000001000 (
b00000000000000000000000000001000 )
13
#7400
03
#7500
13
#7600
03
#7700
13
#7800
b00000000000000000000000001100100 &
b00000000000000000000000011001000 '
03
#7900
1$
1%
1-
1.
b00000000000000000000000001100100 /
b00000000000000000000000011001000 0
b00000000000000000000000001100100 1
b00000000000000000000000011001000 2
13
#8000
03
#8100
b00000000000000000000000100101100 &
b00000000000000000000000110010000 '
b00000000000000000000000000001001 (
b00000000000000000000000000001001 )
b00000000000000000000000100101100 /
b00000000000000000000000110010000 0
b00000000000000000000000100101100 1
b00000000000000000000000110010000 2
13
#8200
03
#8300
b11111111111111111111111000001100 &
b11111111111111111111110110101000 '
b00000000000000000000000000001010 (
b00000000000000000000000000001010 )
b11111111111111111111111000001100 /
b11111111111111111111110110101000 0
b11111111111111111111111000001100 1
b11111111111111111111110110101000 2
13
#8400
03
#8500
0$
0%
b00000000000000000000000000001011 (
b00000000000000000000000000001011 )
0-
0.
13
#8600
03
#8700
13
#8800
03
#8900
13
#9000
b1111111110 #
b00000000000000000001111001100001 &
b00000000000000000010001010111000 '
03
#9100
1$
1%
1-
1.
b00000000000000000001111001100001 /
b00000000000000000010001010111000 0
b00000000000000000001111001100001 1
b00000000000000000010001010111000 2
13
#9200
03
#9300
b0000000000 #
0$
0%
b00000000000000000000000000001100 (
b00000000000000000000000000001100 )
0-
0.
13
#9400
03
#9500
13
#9600
03
#9700
13
#9800
b01111111111111111111111111111111 &
b10000000000000000000000000000000 '
03
#9900
1$
1%
1-
1.
b01111111111111111111111111111111 /
b10000000000000000000000000000000 0
b01111111111111111111111111111111 1
b10000000000000000000000000000000 2
13
#10000
03
#10100
0$
0%
b00000000000000000000000000001101 (
b00000000000000000000000000001101 )
0-
0.
13
#10200
03
#10300
13
#10400
03
#10500
13
#10600
b00000000000000000000000000000000 &
b00000000000000000000000000000000 '
03
#10700
1$
1%
1-
1.
b00000000000000000000000000000000 /
b00000000000000000000000000000000 0
b00000000000000000000000000000000 1
b00000000000000000000000000000000 2
13
#10800
03
#10900
0$
0%
b00000000000000000000000000001110 (
b00000000000000000000000000001110 )
0-
0.
13
#11000
03
#11100
13
#11200
03
#11300
13
#11400
b00000000000000000001000101011100 &
b00000000000000000001010110110011 '
03
#11500
1$
1%
1-
1.
b00000000000000000001000101011100 /
b00000000000000000001010110110011 0
b00000000000000000001000101011100 1
b00000000000000000001010110110011 2
13
#11600
03
#11700
0$
0%
0-
0.
13
#11800
03
#11900
b00000000000000000000000000001111 (
b00000000000000000000000000001111 )
13
#12000
03
#12100
13
#12200
03
#12300
13
#12400
b00000000000000000000011111010000 &
b00000000000000000000101110111000 '
03
#12500
1$
1%
1-
1.
b00000000000000000000011111010000 /
b00000000000000000000101110111000 0
b00000000000000000000011111010000 1
b00000000000000000000101110111000 2
13
#12600
03
#12700
b0000000001 #
b00000000000000000000000000010000 (
b00000000000000000000000000010000 )
b00000000000000000000000000000000 /
b00000000000000000000000000000000 0
b00000000000000000000000000000000 1
b00000000000000000000000000000000 2
13
#12800
03
#12900
b0000000000 #
b00000000000000000000000000010001 (
b00000000000000000000000000010001 )
b00000000000000000000011111010000 /
b00000000000000000000101110111000 0
b00000000000000000000011111010000 1
b00000000000000000000101110111000 2
13
#13000
03
#13100
0$
0%
b00000000000000000000000000010010 (
b00000000000000000000000000010010 )
0-
0.
13
