src/top.sv
`timescale 1ns/100ps

module top #(
) (
    input  logic       a,
    input  logic       b,
    output logic       and_o,
    output logic       xor_o,
    output logic [2:0] and_or_xor
);
    assign and_o = a & b;
    assign xor_o = a ^ b;
    assign and_or_xor = {a & b, a | b, a ^ b};
endmodule

test/tb.sv
`timescale 1ns/100ps

module tb;
    logic a;
    logic b;
    logic and_o;
    logic xor_o;
    logic [2:0] and_or_xor;

    // Instantiate the AND gate
    top uut (
        .a(a),
        .b(b),
        .and_o(and_o),
        .xor_o(xor_o),
        .and_or_xor(and_or_xor)
    );

    initial begin
        $dumpfile("sim_out/wave.vcd");
        $dumpvars(0, tb);
    end

    // Clock not needed, just stimulus
    initial begin
        
        // Print header
        $display("Time\t a b | AND XOR");
        $display("----------------");

        // Test all combinations
        a = 0; b = 0; #10 $display("%0t\t %b %b | %b", $time, a, b, and_o, xor_o);
        a = 0; b = 1; #10 $display("%0t\t %b %b | %b", $time, a, b, and_o, xor_o);
        a = 1; b = 0; #10 $display("%0t\t %b %b | %b", $time, a, b, and_o, xor_o);
        a = 1; b = 1; #10 $display("%0t\t %b %b | %b", $time, a, b, and_o, xor_o);
        a = 0; b = 0; #10 $display("%0t\t %b %b | %b", $time, a, b, and_o, xor_o);
        a = 0; b = 1; #10 $display("%0t\t %b %b | %b", $time, a, b, and_o, xor_o);
        a = 1; b = 0; #10 $display("%0t\t %b %b | %b", $time, a, b, and_o, xor_o);
        a = 1; b = 1; #10 $display("%0t\t %b %b | %b", $time, a, b, and_o, xor_o);

        $display("Testbench finished!");
        $finish;
    end
endmodule

.github/outputs/wave.vcd
$version Generated by VerilatedVcd $end
$timescale 100ps $end
 $scope module TOP $end
  $scope module tb $end
   $var wire 1 # a $end
   $var wire 1 $ b $end
   $var wire 1 % and_o $end
   $var wire 1 & xor_o $end
   $var wire 3 ' and_or_xor [2:0] $end
   $scope module uut $end
    $var wire 1 # a $end
    $var wire 1 $ b $end
    $var wire 1 % and_o $end
    $var wire 1 & xor_o $end
    $var wire 3 ' and_or_xor [2:0] $end
   $upscope $end
  $upscope $end
 $upscope $end
$enddefinitions $end


#0
0#
0$
0%
0&
b000 '
#100
1$
1&
b011 '
#200
1#
0$
#300
1$
1%
0&
b110 '
#400
0#
0$
0%
b000 '
#500
1$
1&
b011 '
#600
1#
0$
#700
1$
1%
0&
b110 '
